odoo8_addon_account_outstanding_payment-8.0.1.0.0.99.dev1-py2.7-nspkg.pth
odoo8_addon_account_outstanding_payment-8.0.1.0.0.99.dev1.dist-info/METADATA
odoo8_addon_account_outstanding_payment-8.0.1.0.0.99.dev1.dist-info/RECORD
odoo8_addon_account_outstanding_payment-8.0.1.0.0.99.dev1.dist-info/WHEEL
odoo8_addon_account_outstanding_payment-8.0.1.0.0.99.dev1.dist-info/namespace_packages.txt
odoo8_addon_account_outstanding_payment-8.0.1.0.0.99.dev1.dist-info/top_level.txt
odoo_addons/account_outstanding_payment/README.rst
odoo_addons/account_outstanding_payment/__init__.py
odoo_addons/account_outstanding_payment/__openerp__.py
odoo_addons/account_outstanding_payment/models/__init__.py
odoo_addons/account_outstanding_payment/models/account_config_settings.py
odoo_addons/account_outstanding_payment/models/account_invoice.py
odoo_addons/account_outstanding_payment/models/account_move_line.py
odoo_addons/account_outstanding_payment/security/ir.model.access.csv
odoo_addons/account_outstanding_payment/static/description/icon.png
odoo_addons/account_outstanding_payment/static/src/css/account_outstanding_payment.css
odoo_addons/account_outstanding_payment/static/src/js/account_outstanding_payment.js
odoo_addons/account_outstanding_payment/static/src/xml/account_payment.xml
odoo_addons/account_outstanding_payment/tests/__init__.py
odoo_addons/account_outstanding_payment/tests/test_account_outstanding_payment.py
odoo_addons/account_outstanding_payment/views/account_config_settings_view.xml
odoo_addons/account_outstanding_payment/views/account_invoice_view.xml
odoo_addons/account_outstanding_payment/views/templates.xml
